lunarcrush/__init__.py
lunarcrush/base.py
lunarcrush/lcv2.py
lunarcrush/lcv3.py
lunarcrush-2.0.5.dist-info/LICENSE
lunarcrush-2.0.5.dist-info/METADATA
lunarcrush-2.0.5.dist-info/WHEEL
lunarcrush-2.0.5.dist-info/top_level.txt
lunarcrush-2.0.5.dist-info/RECORD
