Metadata-Version: 2.1
Name: lunarcrush
Version: 2.0.5
Summary: Unofficial LunarCrush API v2 Wrapper for Python.
Author-email: saizk <sergioaizcorbe@hotmail.com>
License: MIT License
Project-URL: Homepage, https://github.com/saizk/LunarCrushAPI
Project-URL: Bug Tracker, https://github.com/saizk/LunarCrushAPI/issues
Classifier: Programming Language :: Python :: 3
Classifier: Programming Language :: Python :: 3.6
Classifier: Programming Language :: Python :: 3.7
Classifier: Programming Language :: Python :: 3.8
Classifier: Programming Language :: Python :: 3.9
Classifier: Programming Language :: Python :: 3.10
Classifier: License :: OSI Approved :: MIT License
Classifier: Operating System :: OS Independent
Requires-Python: >=3.6
License-File: LICENSE
